Workbook

Sheet README
A1: Cook County Transportation Obligations — FFY2025
A3: Source
A4: CMAP FFY 2025 Annual Obligation Report (Northeastern Illinois / CMAP region), https://cmap.illinois.gov/wp-content/uploads/FFY2025_Obligations_NE_Illinois_Report.pdf
A5: Covers federal fiscal year October 1, 2024 - September 30, 2025. As of this workbook's creation, this is the only obligations report processed; add future years' reports by appending rows to the Exploded_Detail_Relevant and *_Detail tabs (a Fiscal Year column is already present on every tab for that purpose), then extend each summary tab's SUMIFS/COUNTIFS ranges and add new key rows for any new Fiscal Year x Table x Type x Municipality combinations.
A7: Purpose
A8: Built to support Cook County pedestrian-crash research (crosswalk-distances-cc project): a dataset of street/roadway capital investment "facilities" (signal, intersection, roadway, bike/ped, safety, and bridge projects) by Cook County municipality and project type, as a candidate explanatory factor for pedestrian-motor vehicle crash distributions.
A10: Tabs
A11: Summary_Type_Municipality — Fiscal Year x Table x Project Type x Municipality, STREET-DESIGN-RELEVANT projects only, Cook County only. SUMIFS/COUNTIFS formulas over Exploded_Detail_Relevant.
A12: By_Municipality — same filter, rolled up to Fiscal Year x Municipality only. Formulas over Exploded_Detail_Relevant.
A13: By_Type — same filter, rolled up to Fiscal Year x Table x Project Type only. Formulas over Exploded_Detail_Relevant.
A14: Exploded_Detail_Relevant — one row per (project-phase record x municipality), for STREET-DESIGN-RELEVANT, Cook-County projects only. This is the source data every summary-tab formula reads from; edit or extend it (and the three summary tabs' ranges) rather than editing summary totals directly.
A15: FHWA_Obligations_Detail — every FHWA obligation record touching Cook County (unfiltered by relevance), one row per project-phase as reported in the source PDF (NOT exploded by municipality).
... A25: Amounts are as obligated/authorized in FFY2025 for a specific project phase (e.g., design, ROW, construction) -- not necessarily a project's total cost, and a single project can have multiple obligation line items (visible as repeated TIP IDs in the detail tabs).

Sheet Exploded_Detail_Relevant
A1: Fiscal Year | B1: Table | C1: TIP ID | D1: Project Title | E1: Project Type | F1: Municipality | G1: Amount | H1: Includes Bike/Ped Elements | I1: Includes ADA Elements | J1: Includes Safety Elements
A2: FFY2025 | B2: AC Authorization | C2: 06-23-0018 | D2: Ill 50 Cicero Ave - US 12/20 (95th St) to 123rd Pl | E2: Road Maintenance | F2: Alsip | G2: 8240000 | H2: No | I2: No | J2: No
A3: FFY2025 | B3: AC Authorization | C3: 06-24-0041 | D3: Pulaski Rd/Crawford Ave - 103rd St to 123rd St | E3: Road Maintenance | F3: Alsip | G3: 4160000 | H3: Yes | I3: Yes | J3: No
A4: FFY2025 | B4: AC Authorization | C4: 03-25-0005 | D4: Arlington Heights ComEd RIght-of-Way Multi- Use Trail | E4: Bicycle & Pedestrian | F4: Arlington Heights | G4: 480000 | H4: Yes | I4: Yes | J4: No
A5: FFY2025 | B5: FHWA Obligation | C5: 03-25-0005 | D5: Arlington Heights ComEd RIght-of-Way Multi- Use Trail | E5: Bicycle & Pedestrian | F5: Arlington Heights | G5: 480000 | H5: Yes | I5: Yes | J5: No
A6: FFY2025 | B6: AC Authorization | C6: 03-19-0002 | D6: Ill 53 - Lake-Cook Rd to Ill 62 (Algonquin Rd) and S of US 12 (Rand Rd) to Ill 72 (Higgins Rd), At I-90 (Jane Addams Memorial Tollway), Ill 58 (Golf Rd) & Woodfield Rd | E6: Bridge Repair, Rehab, or Replace | F6: Arlington Heights | G6: 6875000 | H6: Yes | I6: Yes | J6: Yes
A7: FFY2025 | B7: FHWA Obligation | C7: 03-19-0002 | D7: Ill 53 - Lake-Cook Rd to Ill 62 (Algonquin Rd) and S of US 12 (Rand Rd) to Ill 72 (Higgins Rd), At I-90 (Jane Addams Memorial Tollway), Ill 58 (Golf Rd) & Woodfield Rd | E7: Bridge Repair, Rehab, or Replace | F7: Arlington Heights | G7: 9696318 | H7: Yes | I7: Yes | J7: Yes
A8: FFY2025 | B8: FHWA Obligation | C8: 03-19-0002 | D8: Ill 53 - Lake-Cook Rd to Ill 62 (Algonquin Rd) and S of US 12 (Rand Rd) to Ill 72 (Higgins Rd), At I-90 (Jane Addams Memorial Tollway), Ill 58 (Golf Rd) & Woodfield Rd | E8: Bridge Repair, Rehab, or Replace | F8: Arlington Heights | G8: 34631474 | H8: Yes | I8: Yes | J8: Yes
A9: FFY2025 | B9: FHWA Obligation | C9: 03-19-0002 | D9: Ill 53 - Lake-Cook Rd to Ill 62 (Algonquin Rd) and S of US 12 (Rand Rd) to Ill 72 (Higgins Rd), At I-90 (Jane Addams Memorial Tollway), Ill 58 (Golf Rd) & Woodfield Rd | E9: Bridge Repair, Rehab, or Replace | F9: Arlington Heights | G9: 16253 | H9: Yes | I9: Yes | J9: Yes
A10: FFY2025 | B10: FHWA Obligation | C10: 03-19-0002 | D10: Ill 53 - Lake-Cook Rd to Ill 62 (Algonquin Rd) and S of US 12 (Rand Rd) to Ill 72 (Higgins Rd), At I-90 (Jane Addams Memorial Tollway), Ill 58 (Golf Rd) & Woodfield Rd | E10: Bridge Repair, Rehab, or Replace | F10: Arlington Heights | G10: 86904481 | H10: Yes | I10: Yes | J10: Yes
A11: FFY2025 | B11: AC Authorization | C11: 03-06-0006 | D11: IL 62 Algonquin Rd at New Wilke Rd | E11: Intersection/Interchange Improvements | F11: Arlington Heights | G11: 2956000 | H11: Yes | I11: Yes | J11: No
A12: FFY2025 | B12: AC Authorization | C12: 03-24-0004 | D12: Various Routes at Various Locations | E12: Intersection/Interchange Improvements | F12: Arlington Heights | G12: 2475000 | H12: No | I12: No | J12: No
A13: FFY2025 | B13: FHWA Obligation | C13: 03-06-0006 | D13: IL 62 Algonquin Rd at New Wilke Rd | E13: Intersection/Interchange Improvements | F13: Arlington Heights | G13: 152000 | H13: Yes | I13: Yes | J13: No
... A491: FFY2025 | B491: AC Authorization | C491: 12-24-0026 | D491: Various - signal modernization at various locations in Cook, & Will | E491: Intersection/Interchange Improvements | F491: Worth | G491: 3150000 | H491: No | I491: No | J491: No

Sheet Summary_Type_Municipality
A1: Fiscal Year | B1: Table | C1: Project Type | D1: Municipality | E1: Obligated_Amount_Sum | F1: Project_Count
A2: FFY2025 | B2: AC Authorization | C2: Road Maintenance | D2: Alsip | E2: =SUMIFS(Exploded_Detail_Relevant!$G$2:$G$491,Exploded_Detail_Relevant!$A$2:$A$491,$A2,Exploded_Detail_Relevant!$B$2:$B$491,$B2,Exploded_Detail_Relevant!$E$2:$E$491,$C2,Exploded_Detail_Relevant!$F$2:$F$491,$D2) -> 12400000 | F2: =COUNTIFS(Exploded_Detail_Relevant!$A$2:$A$491,$A2,Exploded_Detail_Relevant!$B$2:$B$491,$B2,Exploded_Detail_Relevant!$E$2:$E$491,$C2,Exploded_Detail_Relevant!$F$2:$F$491,$D2) -> 2
A3: FFY2025 | B3: AC Authorization | C3: Bicycle & Pedestrian | D3: Arlington Heights | E3: =SUMIFS(Exploded_Detail_Relevant!$G$2:$G$491,Exploded_Detail_Relevant!$A$2:$A$491,$A3,Exploded_Detail_Relevant!$B$2:$B$491,$B3,Exploded_Detail_Relevant!$E$2:$E$491,$C3,Exploded_Detail_Relevant!$F$2:$F$491,$D3) -> 480000 | F3: =COUNTIFS(Exploded_Detail_Relevant!$A$2:$A$491,$A3,Exploded_Detail_Relevant!$B$2:$B$491,$B3,Exploded_Detail_Relevant!$E$2:$E$491,$C3,Exploded_Detail_Relevant!$F$2:$F$491,$D3) -> 1
A4: FFY2025 | B4: FHWA Obligation | C4: Bicycle & Pedestrian | D4: Arlington Heights | E4: =SUMIFS(Exploded_Detail_Relevant!$G$2:$G$491,Exploded_Detail_Relevant!$A$2:$A$491,$A4,Exploded_Detail_Relevant!$B$2:$B$491,$B4,Exploded_Detail_Relevant!$E$2:$E$491,$C4,Exploded_Detail_Relevant!$F$2:$F$491,$D4) -> 480000 | F4: =COUNTIFS(Exploded_Detail_Relevant!$A$2:$A$491,$A4,Exploded_Detail_Relevant!$B$2:$B$491,$B4,Exploded_Detail_Relevant!$E$2:$E$491,$C4,Exploded_Detail_Relevant!$F$2:$F$491,$D4) -> 1
A5: FFY2025 | B5: AC Authorization | C5: Bridge Repair, Rehab, or Replace | D5: Arlington Heights | E5: =SUMIFS(Exploded_Detail_Relevant!$G$2:$G$491,Exploded_Detail_Relevant!$A$2:$A$491,$A5,Exploded_Detail_Relevant!$B$2:$B$491,$B5,Exploded_Detail_Relevant!$E$2:$E$491,$C5,Exploded_Detail_Relevant!$F$2:$F$491,$D5) -> 6875000 | F5: =COUNTIFS(Exploded_Detail_Relevant!$A$2:$A$491,$A5,Exploded_Detail_Relevant!$B$2:$B$491,$B5,Exploded_Detail_Relevant!$E$2:$E$491,$C5,Exploded_Detail_Relevant!$F$2:$F$491,$D5) -> 1
A6: FFY2025 | B6: FHWA Obligation | C6: Bridge Repair, Rehab, or Replace | D6: Arlington Heights | E6: =SUMIFS(Exploded_Detail_Relevant!$G$2:$G$491,Exploded_Detail_Relevant!$A$2:$A$491,$A6,Exploded_Detail_Relevant!$B$2:$B$491,$B6,Exploded_Detail_Relevant!$E$2:$E$491,$C6,Exploded_Detail_Relevant!$F$2:$F$491,$D6) -> 131248526 | F6: =COUNTIFS(Exploded_Detail_Relevant!$A$2:$A$491,$A6,Exploded_Detail_Relevant!$B$2:$B$491,$B6,Exploded_Detail_Relevant!$E$2:$E$491,$C6,Exploded_Detail_Relevant!$F$2:$F$491,$D6) -> 4
A7: FFY2025 | B7: AC Authorization | C7: Intersection/Interchange Improvements | D7: Arlington Heights | E7: =SUMIFS(Exploded_Detail_Relevant!$G$2:$G$491,Exploded_Detail_Relevant!$A$2:$A$491,$A7,Exploded_Detail_Relevant!$B$2:$B$491,$B7,Exploded_Detail_Relevant!$E$2:$E$491,$C7,Exploded_Detail_Relevant!$F$2:$F$491,$D7) -> 5431000 | F7: =COUNTIFS(Exploded_Detail_Relevant!$A$2:$A$491,$A7,Exploded_Detail_Relevant!$B$2:$B$491,$B7,Exploded_Detail_Relevant!$E$2:$E$491,$C7,Exploded_Detail_Relevant!$F$2:$F$491,$D7) -> 2
A8: FFY2025 | B8: FHWA Obligation | C8: Intersection/Interchange Improvements | D8: Arlington Heights | E8: =SUMIFS(Exploded_Detail_Relevant!$G$2:$G$491,Exploded_Detail_Relevant!$A$2:$A$491,$A8,Exploded_Detail_Relevant!$B$2:$B$491,$B8,Exploded_Detail_Relevant!$E$2:$E$491,$C8,Exploded_Detail_Relevant!$F$2:$F$491,$D8) -> 4016846 | F8: =COUNTIFS(Exploded_Detail_Relevant!$A$2:$A$491,$A8,Exploded_Detail_Relevant!$B$2:$B$491,$B8,Exploded_Detail_Relevant!$E$2:$E$491,$C8,Exploded_Detail_Relevant!$F$2:$F$491,$D8) -> 4
A9: FFY2025 | B9: AC Authorization | C9: Road Maintenance | D9: Arlington Heights | E9: =SUMIFS(Exploded_Detail_Relevant!$G$2:$G$491,Exploded_Detail_Relevant!$A$2:$A$491,$A9,Exploded_Detail_Relevant!$B$2:$B$491,$B9,Exploded_Detail_Relevant!$E$2:$E$491,$C9,Exploded_Detail_Relevant!$F$2:$F$491,$D9) -> 4800000 | F9: =COUNTIFS(Exploded_Detail_Relevant!$A$2:$A$491,$A9,Exploded_Detail_Relevant!$B$2:$B$491,$B9,Exploded_Detail_Relevant!$E$2:$E$491,$C9,Exploded_Detail_Relevant!$F$2:$F$491,$D9) -> 1
A10: FFY2025 | B10: AC Authorization | C10: Rail-Highway Grade Separation | D10: Barrington | E10: =SUMIFS(Exploded_Detail_Relevant!$G$2:$G$491,Exploded_Detail_Relevant!$A$2:$A$491,$A10,Exploded_Detail_Relevant!$B$2:$B$491,$B10,Exploded_Detail_Relevant!$E$2:$E$491,$C10,Exploded_Detail_Relevant!$F$2:$F$491,$D10) -> 500000 | F10: =COUNTIFS(Exploded_Detail_Relevant!$A$2:$A$491,$A10,Exploded_Detail_Relevant!$B$2:$B$491,$B10,Exploded_Detail_Relevant!$E$2:$E$491,$C10,Exploded_Detail_Relevant!$F$2:$F$491,$D10) -> 1
A11: FFY2025 | B11: FHWA Obligation | C11: Rail-Highway Grade Separation | D11: Barrington | E11: =SUMIFS(Exploded_Detail_Relevant!$G$2:$G$491,Exploded_Detail_Relevant!$A$2:$A$491,$A11,Exploded_Detail_Relevant!$B$2:$B$491,$B11,Exploded_Detail_Relevant!$E$2:$E$491,$C11,Exploded_Detail_Relevant!$F$2:$F$491,$D11) -> 500000 | F11: =COUNTIFS(Exploded_Detail_Relevant!$A$2:$A$491,$A11,Exploded_Detail_Relevant!$B$2:$B$491,$B11,Exploded_Detail_Relevant!$E$2:$E$491,$C11,Exploded_Detail_Relevant!$F$2:$F$491,$D11) -> 1
A12: FFY2025 | B12: AC Authorization | C12: Safe Routes to Schools | D12: Barrington | E12: =SUMIFS(Exploded_Detail_Relevant!$G$2:$G$491,Exploded_Detail_Relevant!$A$2:$A$491,$A12,Exploded_Detail_Relevant!$B$2:$B$491,$B12,Exploded_Detail_Relevant!$E$2:$E$491,$C12,Exploded_Detail_Relevant!$F$2:$F$491,$D12) -> 250000 | F12: =COUNTIFS(Exploded_Detail_Relevant!$A$2:$A$491,$A12,Exploded_Detail_Relevant!$B$2:$B$491,$B12,Exploded_Detail_Relevant!$E$2:$E$491,$C12,Exploded_Detail_Relevant!$F$2:$F$491,$D12) -> 1
A13: FFY2025 | B13: AC Authorization | C13: Road Maintenance | D13: Barrington Hills | E13: =SUMIFS(Exploded_Detail_Relevant!$G$2:$G$491,Exploded_Detail_Relevant!$A$2:$A$491,$A13,Exploded_Detail_Relevant!$B$2:$B$491,$B13,Exploded_Detail_Relevant!$E$2:$E$491,$C13,Exploded_Detail_Relevant!$F$2:$F$491,$D13) -> 1280000 | F13: =COUNTIFS(Exploded_Detail_Relevant!$A$2:$A$491,$A13,Exploded_Detail_Relevant!$B$2:$B$491,$B13,Exploded_Detail_Relevant!$E$2:$E$491,$C13,Exploded_Detail_Relevant!$F$2:$F$491,$D13) -> 1
... A259: FFY2025 | B259: AC Authorization | C259: Intersection/Interchange Improvements | D259: Worth | E259: =SUMIFS(Exploded_Detail_Relevant!$G$2:$G$491,Exploded_Detail_Relevant!$A$2:$A$491,$A259,Exploded_Detail_Relevant!$B$2:$B$491,$B259,Exploded_Detail_Relevant!$E$2:$E$491,$C259,Exploded_Detail_Relevant!$F$2:$F$491,$D259) -> 3150000 | F259: =COUNTIFS(Exploded_Detail_Relevant!$A$2:$A$491,$A259,Exploded_Detail_Relevant!$B$2:$B$491,$B259,Exploded_Detail_Relevant!$E$2:$E$491,$C259,Exploded_Detail_Relevant!$F$2:$F$491,$D259) -> 1

Sheet By_Municipality
A1: Fiscal Year | B1: Municipality | C1: Obligated_Amount_Sum | D1: Project_Count
A2: FFY2025 | B2: Alsip | C2: =SUMIFS(Exploded_Detail_Relevant!$G$2:$G$491,Exploded_Detail_Relevant!$A$2:$A$491,$A2,Exploded_Detail_Relevant!$F$2:$F$491,$B2) -> 12400000 | D2: =COUNTIFS(Exploded_Detail_Relevant!$A$2:$A$491,$A2,Exploded_Detail_Relevant!$F$2:$F$491,$B2) -> 2
A3: FFY2025 | B3: Arlington Heights | C3: =SUMIFS(Exploded_Detail_Relevant!$G$2:$G$491,Exploded_Detail_Relevant!$A$2:$A$491,$A3,Exploded_Detail_Relevant!$F$2:$F$491,$B3) -> 153331372 | D3: =COUNTIFS(Exploded_Detail_Relevant!$A$2:$A$491,$A3,Exploded_Detail_Relevant!$F$2:$F$491,$B3) -> 14
A4: FFY2025 | B4: Barrington | C4: =SUMIFS(Exploded_Detail_Relevant!$G$2:$G$491,Exploded_Detail_Relevant!$A$2:$A$491,$A4,Exploded_Detail_Relevant!$F$2:$F$491,$B4) -> 1250000 | D4: =COUNTIFS(Exploded_Detail_Relevant!$A$2:$A$491,$A4,Exploded_Detail_Relevant!$F$2:$F$491,$B4) -> 3
A5: FFY2025 | B5: Barrington Hills | C5: =SUMIFS(Exploded_Detail_Relevant!$G$2:$G$491,Exploded_Detail_Relevant!$A$2:$A$491,$A5,Exploded_Detail_Relevant!$F$2:$F$491,$B5) -> 1280000 | D5: =COUNTIFS(Exploded_Detail_Relevant!$A$2:$A$491,$A5,Exploded_Detail_Relevant!$F$2:$F$491,$B5) -> 1
A6: FFY2025 | B6: Bedford Park | C6: =SUMIFS(Exploded_Detail_Relevant!$G$2:$G$491,Exploded_Detail_Relevant!$A$2:$A$491,$A6,Exploded_Detail_Relevant!$F$2:$F$491,$B6) -> 10220291 | D6: =COUNTIFS(Exploded_Detail_Relevant!$A$2:$A$491,$A6,Exploded_Detail_Relevant!$F$2:$F$491,$B6) -> 3
A7: FFY2025 | B7: Bellwood | C7: =SUMIFS(Exploded_Detail_Relevant!$G$2:$G$491,Exploded_Detail_Relevant!$A$2:$A$491,$A7,Exploded_Detail_Relevant!$F$2:$F$491,$B7) -> 1369555 | D7: =COUNTIFS(Exploded_Detail_Relevant!$A$2:$A$491,$A7,Exploded_Detail_Relevant!$F$2:$F$491,$B7) -> 2
A8: FFY2025 | B8: Berkeley | C8: =SUMIFS(Exploded_Detail_Relevant!$G$2:$G$491,Exploded_Detail_Relevant!$A$2:$A$491,$A8,Exploded_Detail_Relevant!$F$2:$F$491,$B8) -> 1477348 | D8: =COUNTIFS(Exploded_Detail_Relevant!$A$2:$A$491,$A8,Exploded_Detail_Relevant!$F$2:$F$491,$B8) -> 3
A9: FFY2025 | B9: Berwyn | C9: =SUMIFS(Exploded_Detail_Relevant!$G$2:$G$491,Exploded_Detail_Relevant!$A$2:$A$491,$A9,Exploded_Detail_Relevant!$F$2:$F$491,$B9) -> 26810772 | D9: =COUNTIFS(Exploded_Detail_Relevant!$A$2:$A$491,$A9,Exploded_Detail_Relevant!$F$2:$F$491,$B9) -> 7
A10: FFY2025 | B10: Blue Island | C10: =SUMIFS(Exploded_Detail_Relevant!$G$2:$G$491,Exploded_Detail_Relevant!$A$2:$A$491,$A10,Exploded_Detail_Relevant!$F$2:$F$491,$B10) -> 1726441 | D10: =COUNTIFS(Exploded_Detail_Relevant!$A$2:$A$491,$A10,Exploded_Detail_Relevant!$F$2:$F$491,$B10) -> 4
A11: FFY2025 | B11: Bridgeview | C11: =SUMIFS(Exploded_Detail_Relevant!$G$2:$G$491,Exploded_Detail_Relevant!$A$2:$A$491,$A11,Exploded_Detail_Relevant!$F$2:$F$491,$B11) -> 1968382 | D11: =COUNTIFS(Exploded_Detail_Relevant!$A$2:$A$491,$A11,Exploded_Detail_Relevant!$F$2:$F$491,$B11) -> 1
A12: FFY2025 | B12: Broadview | C12: =SUMIFS(Exploded_Detail_Relevant!$G$2:$G$491,Exploded_Detail_Relevant!$A$2:$A$491,$A12,Exploded_Detail_Relevant!$F$2:$F$491,$B12) -> 28188070 | D12: =COUNTIFS(Exploded_Detail_Relevant!$A$2:$A$491,$A12,Exploded_Detail_Relevant!$F$2:$F$491,$B12) -> 11
A13: FFY2025 | B13: Brookfield | C13: =SUMIFS(Exploded_Detail_Relevant!$G$2:$G$491,Exploded_Detail_Relevant!$A$2:$A$491,$A13,Exploded_Detail_Relevant!$F$2:$F$491,$B13) -> 6299571 | D13: =COUNTIFS(Exploded_Detail_Relevant!$A$2:$A$491,$A13,Exploded_Detail_Relevant!$F$2:$F$491,$B13) -> 2
... A99: FFY2025 | B99: Worth | C99: =SUMIFS(Exploded_Detail_Relevant!$G$2:$G$491,Exploded_Detail_Relevant!$A$2:$A$491,$A99,Exploded_Detail_Relevant!$F$2:$F$491,$B99) -> 3150000 | D99: =COUNTIFS(Exploded_Detail_Relevant!$A$2:$A$491,$A99,Exploded_Detail_Relevant!$F$2:$F$491,$B99) -> 1

Sheet By_Type
A1: Fiscal Year | B1: Table | C1: Project Type | D1: Obligated_Amount_Sum | E1: Project_Count
A2: FFY2025 | B2: AC Authorization | C2: Bicycle & Pedestrian | D2: =SUMIFS(Exploded_Detail_Relevant!$G$2:$G$491,Exploded_Detail_Relevant!$A$2:$A$491,$A2,Exploded_Detail_Relevant!$B$2:$B$491,$B2,Exploded_Detail_Relevant!$E$2:$E$491,$C2) -> 7501630 | E2: =COUNTIFS(Exploded_Detail_Relevant!$A$2:$A$491,$A2,Exploded_Detail_Relevant!$B$2:$B$491,$B2,Exploded_Detail_Relevant!$E$2:$E$491,$C2) -> 14
A3: FFY2025 | B3: AC Authorization | C3: Bridge Repair, Rehab, or Replace | D3: =SUMIFS(Exploded_Detail_Relevant!$G$2:$G$491,Exploded_Detail_Relevant!$A$2:$A$491,$A3,Exploded_Detail_Relevant!$B$2:$B$491,$B3,Exploded_Detail_Relevant!$E$2:$E$491,$C3) -> 78056254 | E3: =COUNTIFS(Exploded_Detail_Relevant!$A$2:$A$491,$A3,Exploded_Detail_Relevant!$B$2:$B$491,$B3,Exploded_Detail_Relevant!$E$2:$E$491,$C3) -> 17
A4: FFY2025 | B4: AC Authorization | C4: Bridge Routine Maintenance | D4: =SUMIFS(Exploded_Detail_Relevant!$G$2:$G$491,Exploded_Detail_Relevant!$A$2:$A$491,$A4,Exploded_Detail_Relevant!$B$2:$B$491,$B4,Exploded_Detail_Relevant!$E$2:$E$491,$C4) -> 206520000 | E4: =COUNTIFS(Exploded_Detail_Relevant!$A$2:$A$491,$A4,Exploded_Detail_Relevant!$B$2:$B$491,$B4,Exploded_Detail_Relevant!$E$2:$E$491,$C4) -> 11
A5: FFY2025 | B5: AC Authorization | C5: Freight Movement | D5: =SUMIFS(Exploded_Detail_Relevant!$G$2:$G$491,Exploded_Detail_Relevant!$A$2:$A$491,$A5,Exploded_Detail_Relevant!$B$2:$B$491,$B5,Exploded_Detail_Relevant!$E$2:$E$491,$C5) -> 48441164 | E5: =COUNTIFS(Exploded_Detail_Relevant!$A$2:$A$491,$A5,Exploded_Detail_Relevant!$B$2:$B$491,$B5,Exploded_Detail_Relevant!$E$2:$E$491,$C5) -> 16
A6: FFY2025 | B6: AC Authorization | C6: Intersection/Interchange Improvements | D6: =SUMIFS(Exploded_Detail_Relevant!$G$2:$G$491,Exploded_Detail_Relevant!$A$2:$A$491,$A6,Exploded_Detail_Relevant!$B$2:$B$491,$B6,Exploded_Detail_Relevant!$E$2:$E$491,$C6) -> 54291600 | E6: =COUNTIFS(Exploded_Detail_Relevant!$A$2:$A$491,$A6,Exploded_Detail_Relevant!$B$2:$B$491,$B6,Exploded_Detail_Relevant!$E$2:$E$491,$C6) -> 21
A7: FFY2025 | B7: AC Authorization | C7: Rail-Highway Grade Separation | D7: =SUMIFS(Exploded_Detail_Relevant!$G$2:$G$491,Exploded_Detail_Relevant!$A$2:$A$491,$A7,Exploded_Detail_Relevant!$B$2:$B$491,$B7,Exploded_Detail_Relevant!$E$2:$E$491,$C7) -> 11242000 | E7: =COUNTIFS(Exploded_Detail_Relevant!$A$2:$A$491,$A7,Exploded_Detail_Relevant!$B$2:$B$491,$B7,Exploded_Detail_Relevant!$E$2:$E$491,$C7) -> 3
A8: FFY2025 | B8: AC Authorization | C8: Road Expansion | D8: =SUMIFS(Exploded_Detail_Relevant!$G$2:$G$491,Exploded_Detail_Relevant!$A$2:$A$491,$A8,Exploded_Detail_Relevant!$B$2:$B$491,$B8,Exploded_Detail_Relevant!$E$2:$E$491,$C8) -> 34739000 | E8: =COUNTIFS(Exploded_Detail_Relevant!$A$2:$A$491,$A8,Exploded_Detail_Relevant!$B$2:$B$491,$B8,Exploded_Detail_Relevant!$E$2:$E$491,$C8) -> 2
A9: FFY2025 | B9: AC Authorization | C9: Road Maintenance | D9: =SUMIFS(Exploded_Detail_Relevant!$G$2:$G$491,Exploded_Detail_Relevant!$A$2:$A$491,$A9,Exploded_Detail_Relevant!$B$2:$B$491,$B9,Exploded_Detail_Relevant!$E$2:$E$491,$C9) -> 272817403 | E9: =COUNTIFS(Exploded_Detail_Relevant!$A$2:$A$491,$A9,Exploded_Detail_Relevant!$B$2:$B$491,$B9,Exploded_Detail_Relevant!$E$2:$E$491,$C9) -> 87
A10: FFY2025 | B10: AC Authorization | C10: Road Modernization | D10: =SUMIFS(Exploded_Detail_Relevant!$G$2:$G$491,Exploded_Detail_Relevant!$A$2:$A$491,$A10,Exploded_Detail_Relevant!$B$2:$B$491,$B10,Exploded_Detail_Relevant!$E$2:$E$491,$C10) -> 35189683 | E10: =COUNTIFS(Exploded_Detail_Relevant!$A$2:$A$491,$A10,Exploded_Detail_Relevant!$B$2:$B$491,$B10,Exploded_Detail_Relevant!$E$2:$E$491,$C10) -> 16
A11: FFY2025 | B11: AC Authorization | C11: Road Signals & Signs | D11: =SUMIFS(Exploded_Detail_Relevant!$G$2:$G$491,Exploded_Detail_Relevant!$A$2:$A$491,$A11,Exploded_Detail_Relevant!$B$2:$B$491,$B11,Exploded_Detail_Relevant!$E$2:$E$491,$C11) -> 96000 | E11: =COUNTIFS(Exploded_Detail_Relevant!$A$2:$A$491,$A11,Exploded_Detail_Relevant!$B$2:$B$491,$B11,Exploded_Detail_Relevant!$E$2:$E$491,$C11) -> 1
A12: FFY2025 | B12: AC Authorization | C12: Safe Routes to Schools | D12: =SUMIFS(Exploded_Detail_Relevant!$G$2:$G$491,Exploded_Detail_Relevant!$A$2:$A$491,$A12,Exploded_Detail_Relevant!$B$2:$B$491,$B12,Exploded_Detail_Relevant!$E$2:$E$491,$C12) -> 499951 | E12: =COUNTIFS(Exploded_Detail_Relevant!$A$2:$A$491,$A12,Exploded_Detail_Relevant!$B$2:$B$491,$B12,Exploded_Detail_Relevant!$E$2:$E$491,$C12) -> 2
A13: FFY2025 | B13: AC Authorization | C13: Signal Systems | D13: =SUMIFS(Exploded_Detail_Relevant!$G$2:$G$491,Exploded_Detail_Relevant!$A$2:$A$491,$A13,Exploded_Detail_Relevant!$B$2:$B$491,$B13,Exploded_Detail_Relevant!$E$2:$E$491,$C13) -> 198300 | E13: =COUNTIFS(Exploded_Detail_Relevant!$A$2:$A$491,$A13,Exploded_Detail_Relevant!$B$2:$B$491,$B13,Exploded_Detail_Relevant!$E$2:$E$491,$C13) -> 1
... A33: FFY2025 | B33: FHWA Obligation | C33: Transportation Enhancements | D33: =SUMIFS(Exploded_Detail_Relevant!$G$2:$G$491,Exploded_Detail_Relevant!$A$2:$A$491,$A33,Exploded_Detail_Relevant!$B$2:$B$491,$B33,Exploded_Detail_Relevant!$E$2:$E$491,$C33) -> 691619 | E33: =COUNTIFS(Exploded_Detail_Relevant!$A$2:$A$491,$A33,Exploded_Detail_Relevant!$B$2:$B$491,$B33,Exploded_Detail_Relevant!$E$2:$E$491,$C33) -> 1

Sheet FHWA_Obligations_Detail
A1: TIP ID | B1: Project Title | C1: Project Description | D1: Project Type | E1: Project Scope (Work Types) | F1: Programming Agency | G1: Location: County | H1: Location: Municipality | I1: Federal Project | J1: State Job | K1: Federal Program Code | L1: Obligated Amount ($) | M1: Includes Bike/Ped Elements | N1: Includes ADA Elements | O1: Includes Safety Elements | P1: Street Design Relevant | Q1: Fiscal Year | R1: Table
A2: 01-03-0002 | B2: Stony Island Ave Interconnect | C2: Signal Interconnect project, Stony Island Ave from 69th St to 95th St. Includes the intersections at Cornell Dr & 57th Dr. | D2: Signal Systems | E2: [S-TIM] Signals - Interconnects And Timing | F2: CDOT | G2: Cook | H2: Chicago | I2: CKIJ135 | J2: C-88-062-06 | K2: Y400 | L2: 4032000 | M2: No | N2: No | O2: No | P2: TRUE | Q2: FFY2025 | R2: FHWA Obligation
A3: 01-05-0011 | B3: CREATE Western Avenue Corridor from Kedzie Interlocking to Thornton Junction | C3: CREATE WA1-WA5, WA7, WA10,WA11 | D3: Freight Movement | E3: [A-LTS] Safety - Lighting, [E-ADAIMP] Improve ADA Infrastructure (Roadway), [H-RS] Highway/Road - Resurface (with No Lane Widening), [H- STWTR] Highway/Road - Stormwater Infrastucture, [R-IMP] Rail Line - Improve Line, [S-MOD] Signals - Modernization, [U-SIGS] CPS - Signals, [Z- OTHEX] Miscellaneous - Exempt Projects | F3: IDOT OIPI | G3: Cook | H3: Chicago | I3: 0020063 | J3: D-20-054-12 | K3: LY40 | L3: 958001 | M3: Yes | N3: Yes | O3: Yes | P3: TRUE | Q3: FFY2025 | R3: FHWA Obligation
A4: 01-05-0011 | B4: CREATE Western Avenue Corridor from Kedzie Interlocking to Thornton Junction | C4: CREATE WA1-WA5, WA7, WA10,WA11 | D4: Freight Movement | E4: [A-LTS] Safety - Lighting, [E-ADAIMP] Improve ADA Infrastructure (Roadway), [H-RS] Highway/Road - Resurface (with No Lane Widening), [H- STWTR] Highway/Road - Stormwater Infrastucture, [R-IMP] Rail Line - Improve Line, [S-MOD] Signals - Modernization, [U-SIGS] CPS - Signals, [Z- OTHEX] Miscellaneous - Exempt Projects | F4: IDOT OIPI | G4: Cook | H4: Chicago | I4: 2UBT352 | J4: C-20-004-25 | K4: Y430 | L4: 70000000 | M4: Yes | N4: Yes | O4: Yes | P4: TRUE | Q4: FFY2025 | R4: FHWA Obligation
A5: 01-06-0055 | B5: Columbus Av at BRC RR (GS-11) | C5: CREATE GS-11 | D5: Rail-Highway Grade Separation | E5: [H-RRGS] Highway/Road - Railroad Grade Separation | F5: CDOT | G5: Cook | H5: Chicago | I5: 1TM1578 | J5: D-88-001-20 | K5: Y460 | L5: 10189 | M5: No | N5: No | O5: No | P5: TRUE | Q5: FFY2025 | R5: FHWA Obligation
A6: 01-06-0055 | B6: Columbus Av at BRC RR (GS-11) | C6: CREATE GS-11 | D6: Rail-Highway Grade Separation | E6: [H-RRGS] Highway/Road - Railroad Grade Separation | F6: CDOT | G6: Cook | H6: Chicago | I6: J86L198 | J6: C-88-001-22 | K6: Y460 | L6: 43400000 | M6: No | N6: No | O6: No | P6: TRUE | Q6: FFY2025 | R6: FHWA Obligation
A7: 01-09-0031 | B7: I-94 I-90 Kennedy Expy from I-94 Edens Expy to Hubbard St | C7: Bridge Deck Overlay of thirty-eight structures, Bridge Joint Repair, Patching, Sign Maintenance, RR Flagger | D7: Bridge Repair, Rehab, or Replace | E7: [A-OTH] Safety - Other, [B-REPAIR] Bridge/Structure - Reconst/Rehab No Chng in #, Wdth, or Lane, [H-PATCH] Highway/Road - Pavement Patching, [Z-OTHEX] Miscellaneous - Exempt Projects | F7: IDOT D1 Hwys | G7: Cook | H7: Chicago | I7: WKBE580 | J7: C-91-194-20 | K7: Y001 | L7: 15765919 | M7: No | N7: No | O7: Yes | P7: TRUE | Q7: FFY2025 | R7: FHWA Obligation
A8: 01-12-0012 | B8: Canal Street from Madison Street to Taylor Street (Canal St Viaducts) | C8: Reconstruction of the Canal Street viaducts over Union Station and railroad tracks. | D8: Bridge Repair, Rehab, or Replace | E8: [A-LTS] Safety - Lighting, [A-PMRK] Safety - Pavement Marking, [B-REPAIR] Bridge/Structure - Reconst/Rehab No Chng in #, Wdth, or Lane, [B- REPLACE] Bridge/Structure - Replace, [E-ADAIMP] Improve ADA Infrastructure (Roadway), [E-ADAMAINT] Maintain/Repair ADA Infrastructure (Roadway), [E-BIKEMAINT] Maintain Bicycle Facility, [H- ALIGN] Highway/Road - Vertical/Horizontal Alignment (e.g. Clearance), [H- RS] Highway/Road - Resurface (with No Lane Widening), [H-UTIL] Highway/Road - Utility Relocation, [S-MOD] Signals - Modernization, [S- TIM] Signals - Interconnects And Timing | F8: CDOT | G8: Cook | H8: Chicago | I8: K6CZ725 | J8: C-88-002-19 | K8: Y230 | L8: 9480000 | M8: Yes | N8: Yes | O8: Yes | P8: TRUE | Q8: FFY2025 | R8: FHWA Obligation
A9: 01-13-0012 | B9: US 12 US 20 at Stony Island Ave - RSP 112 | C9: LOWER ROADWAY; PUMP STATION; RAILROAD RELOCATION | D9: Intersection/Interchange Improvements | E9: [A-LTS] Safety - Lighting, [B-REPLACE] Bridge/Structure - Replace, [H- INTRC] Highway/Road - Intersection Reconstruction, [Z-OTHEX] Miscellaneous - Exempt Projects | F9: IDOT D1 Hwys | G9: Cook | H9: Chicago | I9: 8U4X907 | J9: D-91-364-20 | K9: Y001 | L9: 2227441 | M9: No | N9: No | O9: Yes | P9: TRUE | Q9: FFY2025 | R9: FHWA Obligation
A10: 01-16-0023 | B10: US 41(Skokie Hwy.)/I-94 (Edens Expy.), IL 173 to I-90 (Kennedy Expy.)/I-94 (Edens Expy.) | C10: Fiber Optic Network (-7000), Surveillance & Changeable Message Signs (- 1000, -3000, -5000), Signing New (-3000), Lighting (-1001, -4100, -4200, - 6000), ITS | D10: Intelligent Transportation Systems | E10: [A-LTS] Safety - Lighting, [H-INFO] Highway/Road - Directional/Informational Signs, [Z-OTHEX] Miscellaneous - Exempt Projects | F10: IDOT D1 Hwys | G10: Cook, Lake | H10: Chicago, Gurnee, Highland Park, Lake Bluff, Lake Forest, Lincolnwood, Morton Grove, North Chicago, Northbrook, Northfield, Park City, Skokie, Wadsworth, Waukegan, Wilmette | I10: B3QI749 | J10: C-91-041-21 | K10: YS30 | L10: 145648 | M10: No | N10: No | O10: Yes | P10: TRUE | Q10: FFY2025 | R10: FHWA Obligation
A11: 01-16-0023 | B11: US 41(Skokie Hwy.)/I-94 (Edens Expy.), IL 173 to I-90 (Kennedy Expy.)/I-94 (Edens Expy.) | C11: Fiber Optic Network (-7000), Surveillance & Changeable Message Signs (- 1000, -3000, -5000), Signing New (-3000), Lighting (-1001, -4100, -4200, - 6000), ITS | D11: Intelligent Transportation Systems | E11: [A-LTS] Safety - Lighting, [H-INFO] Highway/Road - Directional/Informational Signs, [Z-OTHEX] Miscellaneous - Exempt Projects | F11: IDOT D1 Hwys | G11: Cook, Lake | H11: Chicago, Gurnee, Highland Park, Lake Bluff, Lake Forest, Lincolnwood, Morton Grove, North Chicago, Northbrook, Northfield, Park City, Skokie, Wadsworth, Waukegan, Wilmette | I11: FZAB086 | J11: C-91-105-17 | K11: YS30 | L11: 1956539 | M11: No | N11: No | O11: Yes | P11: TRUE | Q11: FFY2025 | R11: FHWA Obligation
A12: 01-18-0007 | B12: Congress Pkwy - At Old Post Office | C12: Bridge Superstructure, Bridge New Deck | D12: Bridge Repair, Rehab, or Replace | E12: [B-SUP] Bridge Superstructure - Repair/Rehab, [Z-OTHEX] Miscellaneous - Exempt Projects | F12: IDOT D1 Hwys | G12: Cook | H12: Chicago | I12: VWWD010 | J12: P-91-037-18 | K12: Z001 | L12: 13140 | M12: No | N12: No | O12: No | P12: TRUE | Q12: FFY2025 | R12: FHWA Obligation
A13: 01-18-0022 | B13: I-94 Bishop Ford Expwy - W of Martin Luther King Dr to US 6 (159th St) | C13: Bridge Deck Overlay, Bridge Joint Replace/Repair, RR Flagger, Resurfacing (Int-2nd), Drainage, Culvert Repair, Bridge Superstructure Rehab, Patching, Lighting | D13: Bridge Routine Maintenance | E13: [A-LTS] Safety - Lighting, [A-OTH] Safety - Other, [B-DECK] Bridge Deck - Repair/Rehab, [B-OVR] Bridge Deck - Overlay, [B-SUP] Bridge Superstructure - Repair/Rehab, [H-CLVT] Highway/Road - Repair/Replace Culvert, [H-PATCH] Highway/Road - Pavement Patching, [H-RS] Highway/Road - Resurface (with No Lane Widening), [Z-OTHEX] Miscellaneous - Exempt Projects | F13: IDOT D1 Hwys | G13: Cook | H13: Calumet City, Chicago, Dolton, South Holland | I13: 2B1H072 | J13: C-91-249-24 | K13: Y001 | L13: 28262658 | M13: No | N13: No | O13: Yes | P13: TRUE | Q13: FFY2025 | R13: FHWA Obligation
... A189: 16-19-0039 | B189: CTA Blue Line Forest Park Reconstruction, RSP -93 | C189: Project will reconstruct and reconfigure the Forest Park Terminal and Yard. The CTAs Forest Park Blue Line Upgrades Project is the first of four phases of the Forest Park Branch. Phase I: new trackwork from Halsted to IMD, an accessible station at Racine, advanced utility work, and a new substation and traction power equipment upgrades at Hermitage. | D189: Guideway Improvements | E189: [R-IMP] Rail Line - Improve Line | F189: CTA | G189: Cook | H189: Chicago, Forest Park, Oak Park | I189: UYS6565 | J189: N-91-002-26 | K189: Y280 | L189: 15805600 | M189: No | N189: No | O189: No | P189: FALSE | Q189: FFY2025 | R189: FHWA Obligation

Sheet AC_Authorizations_Detail
A1: TIP ID | B1: Project Title | C1: Project Description | D1: Project Type | E1: Project Scope (Work Types) | F1: Programming Agency | G1: Location: County | H1: Location: Municipality | I1: Federal Project(s) | J1: Programmed Fund Source(s) | K1: AC Authorization Amount ($) | L1: Includes Bike/Ped Elements | M1: Includes ADA Elements | N1: Includes Safety Elements | O1: Street Design Relevant | P1: Fiscal Year | Q1: Table
A2: 01-05-0012 | B2: CREATE East-West Corridor from Argo Interlocking to CP509 | C2: CREATE East-West Corridor, EW-1, EW-2, EW-3, EW-4 | D2: Freight Movement | E2: [A-LTS] Safety - Lighting, [E-ADAIMP] Improve ADA Infrastructure (Roadway), [H-C/G] Highway/Road - Curb And Gutter, [H-RS] Highway/Road - Resurface (with No Lane Widening), [H-STWTR] Highway/Road - Stormwater Infrastucture, [R-IMP] Rail Line - Improve Line, [S-MOD] Signals - Modernization, [Z-OTHEX] Miscellaneous - Exempt Projects | F2: IDOT OIPI | G2: Cook | H2: Bedford Park, Chicago, McCook, Summit | I2: 91LD405 | J2: Natl Hwy Freight Pgm | K2: 939469 | L2: Yes | M2: Yes | N2: Yes | O2: TRUE | P2: FFY2025 | Q2: AC Authorization
A3: 01-05-0012 | B3: CREATE East-West Corridor from Argo Interlocking to CP509 | C3: CREATE East-West Corridor, EW-1, EW-2, EW-3, EW-4 | D3: Freight Movement | E3: [A-LTS] Safety - Lighting, [E-ADAIMP] Improve ADA Infrastructure (Roadway), [H-C/G] Highway/Road - Curb And Gutter, [H-RS] Highway/Road - Resurface (with No Lane Widening), [H-STWTR] Highway/Road - Stormwater Infrastucture, [R-IMP] Rail Line - Improve Line, [S-MOD] Signals - Modernization, [Z-OTHEX] Miscellaneous - Exempt Projects | F3: IDOT OIPI | G3: Cook | H3: Bedford Park, Chicago, McCook, Summit | I3: KMG3103 | J3: Natl Hwy Freight Pgm | K3: 8841353 | L3: Yes | M3: Yes | N3: Yes | O3: TRUE | P3: FFY2025 | Q3: AC Authorization
A4: 01-05-0012 | B4: CREATE East-West Corridor from Argo Interlocking to CP509 | C4: CREATE East-West Corridor, EW-1, EW-2, EW-3, EW-4 | D4: Freight Movement | E4: [A-LTS] Safety - Lighting, [E-ADAIMP] Improve ADA Infrastructure (Roadway), [H-C/G] Highway/Road - Curb And Gutter, [H-RS] Highway/Road - Resurface (with No Lane Widening), [H-STWTR] Highway/Road - Stormwater Infrastucture, [R-IMP] Rail Line - Improve Line, [S-MOD] Signals - Modernization, [Z-OTHEX] Miscellaneous - Exempt Projects | F4: IDOT OIPI | G4: Cook | H4: Bedford Park, Chicago, McCook, Summit | I4: B9V5881 | J4: Natl Hwy Freight Pgm | K4: 439469 | L4: Yes | M4: Yes | N4: Yes | O4: TRUE | P4: FFY2025 | Q4: AC Authorization
A5: 01-06-0052 | B5: IL 43 (Harlem Avenue) at 65th Street / BRC RR - RSP 109 | C5: CREATE-GS1, 65th St, & 63rd St @ BRC 59th St Line | D5: Rail-Highway Grade Separation | E5: [A-OTH] Safety - Other, [E-ADAMAINT] Maintain/Repair ADA Infrastructure (Roadway), [H-RRGS] Highway/Road - Railroad Grade Separation, [H-RS] Highway/Road - Resurface (with No Lane Widening), [H-STWTR] Highway/Road - Stormwater Infrastucture, [Z-OTHEX] Miscellaneous - Exempt Projects | F5: IDOT D1 Hwys | G5: Cook | H5: Chicago | I5: JEAG627 | J5: NHPP | K5: 742000 | L5: Yes | M5: Yes | N5: Yes | O5: TRUE | P5: FFY2025 | Q5: AC Authorization
A6: 01-06-0055 | B6: Columbus Av at BRC RR (GS-11) | C6: CREATE GS-11 | D6: Rail-Highway Grade Separation | E6: [H-RRGS] Highway/Road - Railroad Grade Separation | F6: CDOT | G6: Cook | H6: Chicago | I6: J86L198 | J6: STP - Locally Prgmd | K6: 10000000 | L6: No | M6: No | N6: No | O6: TRUE | P6: FFY2025 | Q6: AC Authorization
A7: 01-07-0001 | B7: Southwest Service Improvements / 0186 Major - CREATE 75th Street Corridor Improvement Project - RSP 67 | C7: CREATE PASSENGER CORRIDOR: P1-63rd & State; P2-74th St; P3-75th St; P3-75th St+CMB; P4-Grand Crossing; P5-Brighton Park; P6 Canal in Summit; P7-Chicago Ridge. P1-P5 in Chicago. See also 18-09-2400 for EIS for P1-7. | D7: Freight Movement | E7: [A-LTS] Safety - Lighting, [E-ADAIMP] Improve ADA Infrastructure (Roadway), [E-LS] Enhancement - Landscaping, [E-PEDIMP] Improve Pedestrian Facility, [H-C/G] Highway/Road - Curb And Gutter, [H-RS] Highway/Road - Resurface (with No Lane Widening), [H-STWTR] Highway/Road - Stormwater Infrastucture, [R-IMP] Rail Line - Improve Line, [U-SIGS] CPS - Signals | F7: IDOT OIPI | G7: Cook | H7: Chicago, Chicago Ridge | I7: - | J7: Natl Hwy Freight Pgm | K7: 746066 | L7: Yes | M7: Yes | N7: Yes | O7: TRUE | P7: FFY2025 | Q7: AC Authorization
A8: 01-07-0001 | B8: Southwest Service Improvements / 0186 Major - CREATE 75th Street Corridor Improvement Project - RSP 67 | C8: CREATE PASSENGER CORRIDOR: P1-63rd & State; P2-74th St; P3-75th St; P3-75th St+CMB; P4-Grand Crossing; P5-Brighton Park; P6 Canal in Summit; P7-Chicago Ridge. P1-P5 in Chicago. See also 18-09-2400 for EIS for P1-7. | D8: Freight Movement | E8: [A-LTS] Safety - Lighting, [E-ADAIMP] Improve ADA Infrastructure (Roadway), [E-LS] Enhancement - Landscaping, [E-PEDIMP] Improve Pedestrian Facility, [H-C/G] Highway/Road - Curb And Gutter, [H-RS] Highway/Road - Resurface (with No Lane Widening), [H-STWTR] Highway/Road - Stormwater Infrastucture, [R-IMP] Rail Line - Improve Line, [U-SIGS] CPS - Signals | F8: IDOT OIPI | G8: Cook | H8: Chicago, Chicago Ridge | I8: - | J8: Natl Hwy Freight Pgm | K8: 3033934 | L8: Yes | M8: Yes | N8: Yes | O8: TRUE | P8: FFY2025 | Q8: AC Authorization
A9: 01-09-0031 | B9: I-94 I-90 Kennedy Expy from I-94 Edens Expy to Hubbard St | C9: Bridge Deck Overlay of thirty-eight structures, Bridge Joint Repair, Patching, Sign Maintenance, RR Flagger | D9: Bridge Repair, Rehab, or Replace | E9: [A-OTH] Safety - Other, [B-REPAIR] Bridge/Structure - Reconst/Rehab No Chng in #, Wdth, or Lane, [H-PATCH] Highway/Road - Pavement Patching, [Z-OTHEX] Miscellaneous - Exempt Projects | F9: IDOT D1 Hwys | G9: Cook | H9: Chicago | I9: UH3A902 | J9: NHPP | K9: 456329 | L9: No | M9: No | N9: Yes | O9: TRUE | P9: FFY2025 | Q9: AC Authorization
A10: 01-18-0022 | B10: I-94 Bishop Ford Expwy - W of Martin Luther King Dr to US 6 (159th St) | C10: Bridge Deck Overlay, Bridge Joint Replace/Repair, RR Flagger, Resurfacing (Int-2nd), Drainage, Culvert Repair, Bridge Superstructure Rehab, Patching, Lighting | D10: Bridge Routine Maintenance | E10: [A-LTS] Safety - Lighting, [A-OTH] Safety - Other, [B-DECK] Bridge Deck - Repair/Rehab, [B-OVR] Bridge Deck - Overlay, [B-SUP] Bridge Superstructure - Repair/Rehab, [H-CLVT] Highway/Road - Repair/Replace Culvert, [H-PATCH] Highway/Road - Pavement Patching, [H-RS] Highway/Road - Resurface (with No Lane Widening), [Z-OTHEX] Miscellaneous - Exempt Projects | F10: IDOT D1 Hwys | G10: Cook | H10: Calumet City, Chicago, Dolton, South Holland | I10: 2B1H072 | J10: NHPP | K10: 45000000 | L10: No | M10: No | N10: Yes | O10: TRUE | P10: FFY2025 | Q10: AC Authorization
A11: 01-18-0022 | B11: I-94 Bishop Ford Expwy - W of Martin Luther King Dr to US 6 (159th St) | C11: Bridge Deck Overlay, Bridge Joint Replace/Repair, RR Flagger, Resurfacing (Int-2nd), Drainage, Culvert Repair, Bridge Superstructure Rehab, Patching, Lighting | D11: Bridge Routine Maintenance | E11: [A-LTS] Safety - Lighting, [A-OTH] Safety - Other, [B-DECK] Bridge Deck - Repair/Rehab, [B-OVR] Bridge Deck - Overlay, [B-SUP] Bridge Superstructure - Repair/Rehab, [H-CLVT] Highway/Road - Repair/Replace Culvert, [H-PATCH] Highway/Road - Pavement Patching, [H-RS] Highway/Road - Resurface (with No Lane Widening), [Z-OTHEX] Miscellaneous - Exempt Projects | F11: IDOT D1 Hwys | G11: Cook | H11: Calumet City, Chicago, Dolton, South Holland | I11: 2B1H072 | J11: NHPP | K11: 5850000 | L11: No | M11: No | N11: Yes | O11: TRUE | P11: FFY2025 | Q11: AC Authorization
A12: 01-20-0033 | B12: Lincoln Ave - Indiana Ave to Ill 83 (Sibley Blvd) | C12: Standard Overlay, ADA Improvements | D12: Road Maintenance | E12: [E-ADAMAINT] Maintain/Repair ADA Infrastructure (Roadway), [H-RS] Highway/Road - Resurface (with No Lane Widening) | F12: IDOT D1 Hwys | G12: Cook | H12: Chicago, Dolton | I12: 4MJ6604 | J12: STP - State Prgmd Urban | K12: 2000000 | L12: Yes | M12: Yes | N12: No | O12: TRUE | P12: FFY2025 | Q12: AC Authorization
A13: 01-22-0005 | B13: I-290 Eisenhower Expwy - At Keeler Ave | C13: Bridge Replacement, RR Flagger | D13: Bridge Repair, Rehab, or Replace | E13: [A-OTH] Safety - Other, [B-REPLACE] Bridge/Structure - Replace | F13: IDOT D1 Hwys | G13: Cook | H13: Chicago | I13: 1XTC478 | J13: NHPP | K13: 18000000 | L13: No | M13: No | N13: Yes | O13: TRUE | P13: FFY2025 | Q13: AC Authorization
... A121: 15-16-0006 | B121: IL 171 (Archer Ave.) At 95th St. | C121: Intersection Reconstruction, Culvert Rehabilitation, Landscaping | D121: Intersection/Interchange Improvements | E121: [B-REPAIR] Bridge/Structure - Reconst/Rehab No Chng in #, Wdth, or Lane, [E-LS] Enhancement - Landscaping, [H-INTRC] Highway/Road - Intersection Reconstruction | F121: IDOT D1 Hwys | G121: Cook | H121: Unincorporated | I121: 5CJN586 | J121: STP - State Prgmd Urban | K121: 10800000 | L121: Yes | M121: No | N121: No | O121: TRUE | P121: FFY2025 | Q121: AC Authorization

Sheet FTA_Obligations_Detail
A1: TIP ID | B1: Project Title | C1: Project Description | D1: Project Type | E1: Project Scope (Work Types) | F1: Programming Agency | G1: FTA Project # | H1: Federal Fund | I1: Obligated Amount ($) | J1: Includes Bike/Ped Elements | K1: Includes ADA Elements | L1: Includes Safety Elements | M1: Street Design Relevant | N1: Fiscal Year | O1: Table
A2: 01-94-0006 | B2: 254.001 Red Line Extension from US 12 US 20 95th St to 130th - RSP 57 | C2: The proposed Red Line Extension (RLE) project would extend the Red Line from the existing terminal at 95th Street/Dan Ryan to the vicinity of 132nd Street, subject to the availability of funding. The 5.6-mile extension would include four new, accessible stations at 103rd Street, 111th Street, Michigan Avenue, and 130th Street. Other-Federal in FFY 23 are 450k from Areas of Persistent poverty FFY 21 grant and $1.5M in workforce development grants. | D2: Transit Line/Route Expansion | E2: [C-NEW] Station - New, [R-EXP] Rail Line - Expand Line | F2: CTA | G2: IL-2025-001-00 | H2: FTA 5309 (CIG - New Starts) | I2: 746000000 | J2: No | K2: No | L2: No | M2: FALSE | N2: FFY2025 | O2: FTA Obligation
A3: 01-94-0006 | B3: 254.001 Red Line Extension from US 12 US 20 95th St to 130th - RSP 57 | C3: The proposed Red Line Extension (RLE) project would extend the Red Line from the existing terminal at 95th Street/Dan Ryan to the vicinity of 132nd Street, subject to the availability of funding. The 5.6-mile extension would include four new, accessible stations at 103rd Street, 111th Street, Michigan Avenue, and 130th Street. Other-Federal in FFY 23 are 450k from Areas of Persistent poverty FFY 21 grant and $1.5M in workforce development grants. | D3: Transit Line/Route Expansion | E3: [C-NEW] Station - New, [R-EXP] Rail Line - Expand Line | F3: CTA | G3: IL-2025-001-01 | H3: FTA 5309 (CIG - New Starts) | I3: 350000000 | J3: No | K3: No | L3: No | M3: FALSE | N3: FFY2025 | O3: FTA Obligation
A4: 13-24-0001 | B4: FTA Section (FFY 22 and 23) 5310 Enhanced Mobility for Seniors and Individuals with Disabilities (RTA 2022 & 2023 Program of Projects) | C4: Projects that provide enhanced transportation services for Seniors and Individuals with Disabilities throughout the region using FTA Section 5310 funds from FFY 22 and 23. | D4: Transit Operations | E4: [O-C&A] Operations - Contingency And Administration, [O-OPS] Operations - Transit Operating Assistance, [Z-OTHEX] Miscellaneous - Exempt Projects | F4: RTA | G4: IL-2024-004-00 | H4: FTA 5310 Elderly/Disabled | I4: 200000 | J4: No | K4: No | L4: No | M4: FALSE | N4: FFY2025 | O4: FTA Obligation
A5: 13-24-0001 | B5: FTA Section (FFY 22 and 23) 5310 Enhanced Mobility for Seniors and Individuals with Disabilities (RTA 2022 & 2023 Program of Projects) | C5: Projects that provide enhanced transportation services for Seniors and Individuals with Disabilities throughout the region using FTA Section 5310 funds from FFY 22 and 23. | D5: Transit Operations | E5: [O-C&A] Operations - Contingency And Administration, [O-OPS] Operations - Transit Operating Assistance, [Z-OTHEX] Miscellaneous - Exempt Projects | F5: RTA | G5: IL-2024-004-00 | H5: FTA 5310 Elderly/Disabled | I5: 214583 | J5: No | K5: No | L5: No | M5: FALSE | N5: FFY2025 | O5: FTA Obligation
A6: 13-24-0001 | B6: FTA Section (FFY 22 and 23) 5310 Enhanced Mobility for Seniors and Individuals with Disabilities (RTA 2022 & 2023 Program of Projects) | C6: Projects that provide enhanced transportation services for Seniors and Individuals with Disabilities throughout the region using FTA Section 5310 funds from FFY 22 and 23. | D6: Transit Operations | E6: [O-C&A] Operations - Contingency And Administration, [O-OPS] Operations - Transit Operating Assistance, [Z-OTHEX] Miscellaneous - Exempt Projects | F6: RTA | G6: IL-2024-004-00 | H6: FTA 5310 Elderly/Disabled | I6: 17301 | J6: No | K6: No | L6: No | M6: FALSE | N6: FFY2025 | O6: FTA Obligation
A7: 13-24-0001 | B7: FTA Section (FFY 22 and 23) 5310 Enhanced Mobility for Seniors and Individuals with Disabilities (RTA 2022 & 2023 Program of Projects) | C7: Projects that provide enhanced transportation services for Seniors and Individuals with Disabilities throughout the region using FTA Section 5310 funds from FFY 22 and 23. | D7: Transit Operations | E7: [O-C&A] Operations - Contingency And Administration, [O-OPS] Operations - Transit Operating Assistance, [Z-OTHEX] Miscellaneous - Exempt Projects | F7: RTA | G7: IL-2024-004-00 | H7: FTA 5310 Elderly/Disabled | I7: 350000 | J7: No | K7: No | L7: No | M7: FALSE | N7: FFY2025 | O7: FTA Obligation
A8: 13-24-0001 | B8: FTA Section (FFY 22 and 23) 5310 Enhanced Mobility for Seniors and Individuals with Disabilities (RTA 2022 & 2023 Program of Projects) | C8: Projects that provide enhanced transportation services for Seniors and Individuals with Disabilities throughout the region using FTA Section 5310 funds from FFY 22 and 23. | D8: Transit Operations | E8: [O-C&A] Operations - Contingency And Administration, [O-OPS] Operations - Transit Operating Assistance, [Z-OTHEX] Miscellaneous - Exempt Projects | F8: RTA | G8: IL-2024-004-00 | H8: FTA 5310 Elderly/Disabled | I8: 22510 | J8: No | K8: No | L8: No | M8: FALSE | N8: FFY2025 | O8: FTA Obligation
A9: 13-24-0001 | B9: FTA Section (FFY 22 and 23) 5310 Enhanced Mobility for Seniors and Individuals with Disabilities (RTA 2022 & 2023 Program of Projects) | C9: Projects that provide enhanced transportation services for Seniors and Individuals with Disabilities throughout the region using FTA Section 5310 funds from FFY 22 and 23. | D9: Transit Operations | E9: [O-C&A] Operations - Contingency And Administration, [O-OPS] Operations - Transit Operating Assistance, [Z-OTHEX] Miscellaneous - Exempt Projects | F9: RTA | G9: IL-2024-004-00 | H9: FTA 5310 Elderly/Disabled | I9: 80000 | J9: No | K9: No | L9: No | M9: FALSE | N9: FFY2025 | O9: FTA Obligation
A10: 13-24-0001 | B10: FTA Section (FFY 22 and 23) 5310 Enhanced Mobility for Seniors and Individuals with Disabilities (RTA 2022 & 2023 Program of Projects) | C10: Projects that provide enhanced transportation services for Seniors and Individuals with Disabilities throughout the region using FTA Section 5310 funds from FFY 22 and 23. | D10: Transit Operations | E10: [O-C&A] Operations - Contingency And Administration, [O-OPS] Operations - Transit Operating Assistance, [Z-OTHEX] Miscellaneous - Exempt Projects | F10: RTA | G10: IL-2024-004-00 | H10: FTA 5310 Elderly/Disabled | I10: 310000 | J10: No | K10: No | L10: No | M10: FALSE | N10: FFY2025 | O10: FTA Obligation
A11: 13-24-0001 | B11: FTA Section (FFY 22 and 23) 5310 Enhanced Mobility for Seniors and Individuals with Disabilities (RTA 2022 & 2023 Program of Projects) | C11: Projects that provide enhanced transportation services for Seniors and Individuals with Disabilities throughout the region using FTA Section 5310 funds from FFY 22 and 23. | D11: Transit Operations | E11: [O-C&A] Operations - Contingency And Administration, [O-OPS] Operations - Transit Operating Assistance, [Z-OTHEX] Miscellaneous - Exempt Projects | F11: RTA | G11: IL-2024-004-00 | H11: FTA 5310 Elderly/Disabled | I11: 60000 | J11: No | K11: No | L11: No | M11: FALSE | N11: FFY2025 | O11: FTA Obligation
A12: 16-02-0004 | B12: 141.273 Reconstruct Rail Stations | C12: Project will provide for the upgrade and enhancement of CTAs rail stations system-wide. The Refreshed & Renewed Program performs major improvement work at transit operations facilities for both the customer and the internal needs of the Authority. Project will also provide for Customer Assistant Kiosks. | D12: Guideway Improvements | E12: [R-MAINT] Rail Line - Maintain, Rehabilitate, Replace | F12: CTA | G12: IL-2025-028 | H12: FTA 5337 Good Repair | I12: 3000000 | J12: No | K12: No | L12: No | M12: FALSE | N12: FFY2025 | O12: FTA Obligation
A13: 16-03-0011 | B13: 150.028 Implement Security Projects | C13: The HLS Program provides funding to state, local, tribal, and territorial governments, as well as transportation authorities, nonprofit organizations, and the private sector, to improve the nation's readiness in preventing, protecting against, responding to, recovering from and mitigating terrorist attacks, major disasters and other emergencies. | D13: Systems Improvements | E13: [Z-OTHEX] Miscellaneous - Exempt Projects | F13: CTA | G13: IL-2025-028 | H13: FTA 5307 Urban Formula | I13: 6000000 | J13: No | K13: No | L13: No | M13: TRUE | N13: FFY2025 | O13: FTA Obligation
... A150: 18-25-0013 | B150: Yard Improvements - UPR | C150: Yard Improvements on Metra's Union Pacific lines (UP-N, UP-W, UP-NW) | D150: Transit Support Facilities | E150: [F-YRDS] Facility - Towers And Yards | F150: Metra | G150: IL-2025-027-01-00 | H150: FTA 5337 Good Repair | I150: 425000 | J150: No | K150: No | L150: No | M150: FALSE | N150: FFY2025 | O150: FTA Obligation
